openvsc/__init__.py
openvsc/cli.py
openvsc-0.1.0.dist-info/licenses/LICENSE
openvsc-0.1.0.dist-info/METADATA
openvsc-0.1.0.dist-info/WHEEL
openvsc-0.1.0.dist-info/entry_points.txt
openvsc-0.1.0.dist-info/top_level.txt
openvsc-0.1.0.dist-info/RECORD
