Metadata-Version: 2.4
Name: openvsc
Version: 0.1.0
Summary: Open your local repos in VS Code from the CLI
Author: Griffin McManus
License: MIT
Classifier: Programming Language :: Python :: 3
Classifier: License :: OSI Approved :: MIT License
Classifier: Operating System :: OS Independent
Requires-Python: >=3.8
License-File: LICENSE
Dynamic: license-file
